doleus/__init__.py
doleus/annotations/__init__.py
doleus/annotations/base.py
doleus/annotations/classification.py
doleus/annotations/detection.py
doleus/checks/__init__.py
doleus/checks/base.py
doleus/checks/visualization.py
doleus/datasets/__init__.py
doleus/datasets/base.py
doleus/datasets/classification.py
doleus/datasets/detection.py
doleus/metrics/__init__.py
doleus/metrics/calculator.py
doleus/metrics/metric_utils.py
doleus/storage/__init__.py
doleus/storage/ground_truth_store/__init__.py
doleus/storage/ground_truth_store/base.py
doleus/storage/ground_truth_store/classification.py
doleus/storage/ground_truth_store/detection.py
doleus/storage/metadata_store/__init__.py
doleus/storage/metadata_store/store.py
doleus/storage/prediction_store/__init__.py
doleus/storage/prediction_store/base.py
doleus/storage/prediction_store/classification.py
doleus/storage/prediction_store/detection.py
doleus/utils/__init__.py
doleus/utils/data.py
doleus/utils/image_metadata.py
doleus/utils/utils.py
doleus-0.2.4.dist-info/LICENSE
doleus-0.2.4.dist-info/METADATA
doleus-0.2.4.dist-info/NOTICE
doleus-0.2.4.dist-info/WHEEL
doleus-0.2.4.dist-info/RECORD
