Metadata-Version: 2.3
Name: doleus
Version: 0.2.4
Summary: Doleus: Test Your Image-based AI Models on Data Slices
License: Apache-2.0
Author: Hendrik Schulze Bröring
Requires-Python: >=3.11
Classifier: License :: OSI Approved :: Apache Software License
Classifier: Programming Language :: Python :: 3
Classifier: Programming Language :: Python :: 3.11
Classifier: Programming Language :: Python :: 3.12
Classifier: Programming Language :: Python :: 3.13
Requires-Dist: numpy (>=1.21.0,<3.0.0)
Requires-Dist: opencv-python-headless (>=4.5.0,<5.0.0.0)
Requires-Dist: pillow (>=10.0.0,<13.0.0)
Requires-Dist: pytz (>=2023.0)
Requires-Dist: torch (>=2.3.0,<3.0.0)
Requires-Dist: torchmetrics (>=1.0.0,<2.0.0)
Requires-Dist: tqdm (>=4.60.0,<5.0.0)
